[
    {
        "id": "sd_fqqNMHeefqVerwOE",
        "type": "tab",
        "createdDate": "2022-07-24T10:54:03.597Z",
        "label": "all_leave",
        "disabled": false,
        "info": "",
        "functionSeq": 0,
        "generateNext": true,
        "serviceName": "all_leaveComponent"
    },
    {
        "id": "sd_AVFH4J5zlGffvOWe",
        "type": "OnInit",
        "z": "sd_fqqNMHeefqVerwOE",
        "viewType": "common",
        "nodeType": "start",
        "name": "",
        "functionName": "sd_AVFH4J5zlGffvOWe",
        "category": "Lifecycle Events",
        "x": 65,
        "y": 80,
        "wires": [
            [
                "sd_jBehYYQu9Etu5LJD"
            ]
        ],
        "__n_excludedFromValidation__": {},
        "generateNext": true,
        "serviceName": "all_leaveComponent"
    },
    {
        "id": "sd_jBehYYQu9Etu5LJD",
        "type": "PageVariables",
        "z": "sd_fqqNMHeefqVerwOE",
        "viewType": "pages",
        "nodeType": "flow",
        "name": "",
        "inputs": 1,
        "outputs": 1,
        "operation": "set",
        "globalVariables": [
            {
                "textIp": "userMongo",
                "typedIpValue": {
                    "type": "literal",
                    "value": ""
                }
            },
            {
                "textIp": "leaveList",
                "typedIpValue": {
                    "type": "literal",
                    "value": ""
                }
            },
            {
                "textIp": "isEmployee",
                "typedIpValue": {
                    "type": "literal",
                    "value": "false"
                }
            }
        ],
        "functionName": "sd_jBehYYQu9Etu5LJD",
        "category": "Function",
        "x": 185,
        "y": 80,
        "wires": [
            [
                "sd_5Bgq8WlFjlgLyPna"
            ]
        ],
        "__n_excludedFromValidation__": {},
        "generateNext": false,
        "generated": true,
        "serviceName": "all_leaveComponent"
    },
    {
        "id": "sd_5Bgq8WlFjlgLyPna",
        "type": "Storage",
        "z": "sd_fqqNMHeefqVerwOE",
        "viewType": "client-pages",
        "nodeType": "flow",
        "name": "",
        "operationType": "getItem",
        "storageType": "sessionStorage",
        "outputs": 1,
        "key": {
            "type": "str",
            "value": "user"
        },
        "value": {},
        "resultMapping": {
            "type": "this.page",
            "value": "userMongo"
        },
        "functionName": "sd_5Bgq8WlFjlgLyPna",
        "category": "Storage",
        "x": 285,
        "y": 80,
        "wires": [
            [
                "sd_WiUKJxXVrg6iqeEd"
            ]
        ],
        "__n_excludedFromValidation__": {},
        "generateNext": false,
        "generated": true,
        "serviceName": "all_leaveComponent"
    },
    {
        "id": "sd_PsnKfYWFcZeOY1vP",
        "type": "PageStart",
        "z": "sd_fqqNMHeefqVerwOE",
        "viewType": "pages",
        "nodeType": "start",
        "name": "fetchLeave",
        "outputs": 1,
        "inputVariables": [],
        "localVariables": [],
        "flow_type": "sync",
        "functionName": "fetchLeave",
        "category": "General",
        "x": 100,
        "y": 260,
        "wires": [
            [
                "sd_PdOS9BbwKeRE7ZhD"
            ]
        ],
        "__n_excludedFromValidation__": {},
        "generateNext": true,
        "serviceName": "all_leaveComponent"
    },
    {
        "id": "sd_PdOS9BbwKeRE7ZhD",
        "type": "Script",
        "z": "sd_fqqNMHeefqVerwOE",
        "viewType": "common",
        "nodeType": "flow",
        "name": "",
        "script": "bh.input.path = page.isEmployee ? 'getPendingRequests' : 'getAllLeaveRequests';\nbh.input.method = 'POST';\n\nbh.input.body =  {\n    email: page.userMongo[0].email\n};\n",
        "functionName": "sd_PdOS9BbwKeRE7ZhD",
        "category": "Function",
        "x": 240,
        "y": 260,
        "wires": [
            [
                "sd_mVROWvgjk3A1GXdj"
            ]
        ],
        "__n_excludedFromValidation__": {},
        "generateNext": false,
        "generated": true
    },
    {
        "id": "sd_mVROWvgjk3A1GXdj",
        "type": "PageCallService",
        "z": "sd_fqqNMHeefqVerwOE",
        "viewType": "pages",
        "nodeType": "flow",
        "name": "",
        "outputs": 1,
        "isValidNode": true,
        "noerr": 0,
        "service": {
            "id": "sd_MSma9GJuXg98ZzJs",
            "type": "tab",
            "createdDate": "2022-07-25T20:55:29.182Z",
            "label": "client_service",
            "disabled": false,
            "info": "",
            "functionSeq": 0
        },
        "flow": {
            "flowId": "sd_e3SpyZ5sB2xLCtH4",
            "flowName": "dynamicApiCall"
        },
        "inputVariables": [
            {
                "key": "path",
                "map": true,
                "valueType": "bh.input",
                "value": "path"
            },
            {
                "key": "body",
                "map": true,
                "valueType": "bh.input",
                "value": "body"
            },
            {
                "key": "method",
                "map": true,
                "valueType": "bh.input",
                "value": "method"
            }
        ],
        "outputMapping": [
            {
                "mapVarType": "local",
                "key": "results",
                "valueType": "this.page",
                "value": "leaveList",
                "mapVarName": "results",
                "localVar": "this.page.leaveList"
            }
        ],
        "serviceImportPath": "app/sd-services/client_service",
        "startName": "dynamicApiCall",
        "inputParams": [
            "bh.input.path",
            "bh.input.body",
            "bh.input.method"
        ],
        "accept_bh": false,
        "accept_csd": true,
        "functionName": "sd_mVROWvgjk3A1GXdj",
        "category": "General",
        "x": 345,
        "y": 260,
        "wires": [
            [
                "sd_2TNFGjiIOKA8ZVQb"
            ]
        ],
        "__n_excludedFromValidation__": {},
        "generateNext": false,
        "generated": true
    },
    {
        "id": "sd_WiUKJxXVrg6iqeEd",
        "type": "PageCallService",
        "z": "sd_fqqNMHeefqVerwOE",
        "viewType": "pages",
        "nodeType": "flow",
        "name": "",
        "outputs": 1,
        "isValidNode": true,
        "noerr": 0,
        "service": {
            "id": "sd_fqqNMHeefqVerwOE",
            "type": "tab",
            "createdDate": "2022-07-24T10:54:03.597Z",
            "label": "all_leave",
            "disabled": false,
            "info": "",
            "functionSeq": 0
        },
        "flow": {
            "flowId": "sd_PsnKfYWFcZeOY1vP",
            "flowName": "fetchLeave"
        },
        "inputVariables": [],
        "outputMapping": [],
        "serviceImportPath": "./all_leave",
        "startName": "fetchLeave",
        "inputParams": [],
        "accept_bh": false,
        "accept_csd": false,
        "functionName": "sd_WiUKJxXVrg6iqeEd",
        "category": "General",
        "x": 400,
        "y": 80,
        "wires": [
            [
                "sd_nCJ5Cqd3C8aPpjmw"
            ]
        ],
        "__n_excludedFromValidation__": {},
        "generateNext": false,
        "generated": true
    },
    {
        "id": "sd_2TNFGjiIOKA8ZVQb",
        "type": "Script",
        "z": "sd_fqqNMHeefqVerwOE",
        "viewType": "common",
        "nodeType": "flow",
        "name": "",
        "script": "var options = { year: 'numeric', month: 'long', day: 'numeric' };\n\nfor (var i = 0; i < page.leaveList.length; i++){\n    page.leaveList[i].startDate = transformDate(page.leaveList[i].startDate)\n    page.leaveList[i].endDate =  transformDate(page.leaveList[i].endDate)\n}\npage.leaveList = page.leaveList.reverse()\nfunction transformDate(date){\n    \n date = Date.parse(date);\n date = new Date(date);\n date = date.toLocaleDateString(\"en-US\", options);\n\n return date\n}",
        "functionName": "sd_2TNFGjiIOKA8ZVQb",
        "category": "Function",
        "x": 440,
        "y": 260,
        "wires": [
            []
        ],
        "__n_excludedFromValidation__": {},
        "generateNext": false,
        "generated": true
    },
    {
        "id": "sd_nCJ5Cqd3C8aPpjmw",
        "type": "Script",
        "z": "sd_fqqNMHeefqVerwOE",
        "viewType": "common",
        "nodeType": "flow",
        "name": "",
        "script": "page.isEmployee = page.userMongo[0].role !== 'Line Manager' ? true : false;\nconsole.log('all leave',page)\n",
        "functionName": "sd_nCJ5Cqd3C8aPpjmw",
        "category": "Function",
        "x": 525,
        "y": 80,
        "wires": [
            []
        ],
        "__n_excludedFromValidation__": {},
        "generateNext": false,
        "generated": true
    },
    {
        "id": "sd_WROhBYs35Bnnh1SN",
        "type": "PageStart",
        "z": "sd_fqqNMHeefqVerwOE",
        "viewType": "pages",
        "nodeType": "start",
        "name": "leaveDetail",
        "outputs": 1,
        "inputVariables": [
            {
                "key": "owner",
                "defaultValue": {
                    "type": "any",
                    "value": ""
                },
                "output": false
            },
            {
                "key": "id",
                "defaultValue": {
                    "type": "any",
                    "value": ""
                },
                "output": false
            }
        ],
        "localVariables": [],
        "flow_type": "sync",
        "functionName": "leaveDetail",
        "category": "General",
        "x": 85,
        "y": 380,
        "wires": [
            [
                "sd_Zq9iUZMSYAR5eRAx"
            ]
        ],
        "__n_excludedFromValidation__": {},
        "generateNext": true,
        "serviceName": "all_leaveComponent"
    },
    {
        "id": "sd_SgR1KUzFyJAHw2xB",
        "type": "Navigation",
        "z": "sd_fqqNMHeefqVerwOE",
        "viewType": "client-pages",
        "nodeType": "flow",
        "name": "",
        "path": "/home/admin/details",
        "pathMap": "",
        "pathparams": "",
        "pathparamsMap": "",
        "qparams": "",
        "qparamsMap": "",
        "qparamsArray": "",
        "resultMapping": "",
        "functionName": "sd_SgR1KUzFyJAHw2xB",
        "category": "Navigation",
        "x": 445,
        "y": 380,
        "wires": [
            []
        ],
        "__n_excludedFromValidation__": {},
        "generateNext": false,
        "generated": true
    },
    {
        "id": "sd_2u8FO3Ow5kXCQAhL",
        "type": "PageStart",
        "z": "sd_fqqNMHeefqVerwOE",
        "viewType": "pages",
        "nodeType": "start",
        "name": "openDialog",
        "outputs": 1,
        "inputVariables": [
            {
                "key": "leaveDetails",
                "defaultValue": {
                    "type": "any",
                    "value": ""
                },
                "output": false
            }
        ],
        "localVariables": [],
        "flow_type": "sync",
        "functionName": "openDialog",
        "category": "General",
        "x": 65,
        "y": 620,
        "wires": [
            [
                "sd_D2MloTr8AnfA7Y7g"
            ]
        ],
        "__n_excludedFromValidation__": {},
        "generateNext": true,
        "serviceName": "all_leaveComponent"
    },
    {
        "id": "sd_D2MloTr8AnfA7Y7g",
        "type": "OpenDialog",
        "z": "sd_fqqNMHeefqVerwOE",
        "viewType": "common",
        "nodeType": "flow",
        "name": "",
        "outputs": 4,
        "flow": {
            "flowId": "sd_VENuDC99MMwEMfCo",
            "label": "dialog_box_details"
        },
        "relativePath": "../../aa_base/dialog_box_details",
        "data": "bh.input.leaveDetails",
        "ariaDescribedBy": "this.page",
        "ariaLabel": "this.page",
        "ariaLabelledBy": "this.page",
        "autoFocus": "this.page",
        "backdropClass": "this.page",
        "closeOnNavigation": "this.page",
        "direction": "this.page",
        "disableClose": "this.page",
        "hasBackdrop": "this.page",
        "height": "this.page",
        "maxHeight": "this.page",
        "minHeight": "this.page",
        "width": "this.page",
        "maxWidth": "this.page",
        "minWidth": "this.page",
        "panelClass": "this.page",
        "position": "this.page",
        "restoreFocus": "this.page",
        "role": "this.page",
        "resultMapping": "this.page",
        "functionName": "sd_D2MloTr8AnfA7Y7g",
        "category": "Dialog",
        "x": 200,
        "y": 620,
        "wires": [
            [],
            [],
            [],
            []
        ],
        "__ssdTypeInputs__": {
            "data": {
                "type": "bh.input",
                "value": "leaveDetails",
                "constant": false
            },
            "ariaDescribedBy": {
                "type": "this.page",
                "value": "",
                "constant": false
            },
            "ariaLabel": {
                "type": "this.page",
                "value": "",
                "constant": false
            },
            "ariaLabelledBy": {
                "type": "this.page",
                "value": "",
                "constant": false
            },
            "autoFocus": {
                "type": "this.page",
                "value": "",
                "constant": false
            },
            "backdropClass": {
                "type": "this.page",
                "value": "",
                "constant": false
            },
            "closeOnNavigation": {
                "type": "this.page",
                "value": "",
                "constant": false
            },
            "direction": {
                "type": "this.page",
                "value": "",
                "constant": false
            },
            "disableClose": {
                "type": "this.page",
                "value": "",
                "constant": false
            },
            "hasBackdrop": {
                "type": "this.page",
                "value": "",
                "constant": false
            },
            "height": {
                "type": "this.page",
                "value": "",
                "constant": false
            },
            "maxHeight": {
                "type": "this.page",
                "value": "",
                "constant": false
            },
            "minHeight": {
                "type": "this.page",
                "value": "",
                "constant": false
            },
            "width": {
                "type": "this.page",
                "value": "",
                "constant": false
            },
            "maxWidth": {
                "type": "this.page",
                "value": "",
                "constant": false
            },
            "minWidth": {
                "type": "this.page",
                "value": "",
                "constant": false
            },
            "panelClass": {
                "type": "this.page",
                "value": "",
                "constant": false
            },
            "position": {
                "type": "this.page",
                "value": "",
                "constant": false
            },
            "restoreFocus": {
                "type": "this.page",
                "value": "",
                "constant": false
            },
            "role": {
                "type": "this.page",
                "value": "",
                "constant": false
            },
            "resultMapping": {
                "type": "this.page",
                "value": "",
                "constant": false
            }
        },
        "__n_excludedFromValidation__": {},
        "generateNext": false,
        "generated": true
    },
    {
        "id": "sd_qqLalTf6m0mPICQh",
        "type": "Storage",
        "z": "sd_fqqNMHeefqVerwOE",
        "viewType": "client-pages",
        "nodeType": "flow",
        "name": "",
        "operationType": "setItem",
        "storageType": "sessionStorage",
        "outputs": 1,
        "key": {
            "type": "str",
            "value": "leaveData"
        },
        "value": {
            "type": "bh",
            "value": "leaveData"
        },
        "resultMapping": {},
        "functionName": "sd_qqLalTf6m0mPICQh",
        "category": "Storage",
        "x": 265,
        "y": 380,
        "wires": [
            [
                "sd_mhRJkOi4nAXRZ0Pe"
            ]
        ],
        "__n_excludedFromValidation__": {},
        "generateNext": false,
        "generated": true
    },
    {
        "id": "sd_Zq9iUZMSYAR5eRAx",
        "type": "Script",
        "z": "sd_fqqNMHeefqVerwOE",
        "viewType": "common",
        "nodeType": "flow",
        "name": "",
        "script": "let tempData = page.leaveList.filter(item => item['_id'] === bh.input.id);\nbh.leaveData = tempData.length > 0 ? tempData[0] : [];",
        "functionName": "sd_Zq9iUZMSYAR5eRAx",
        "category": "Function",
        "x": 185,
        "y": 380,
        "wires": [
            [
                "sd_qqLalTf6m0mPICQh"
            ]
        ],
        "__n_excludedFromValidation__": {},
        "generateNext": false,
        "generated": true
    },
    {
        "id": "sd_mhRJkOi4nAXRZ0Pe",
        "type": "Storage",
        "z": "sd_fqqNMHeefqVerwOE",
        "viewType": "client-pages",
        "nodeType": "flow",
        "name": "",
        "operationType": "setItem",
        "storageType": "sessionStorage",
        "outputs": 1,
        "key": {
            "type": "str",
            "value": "leaveOwner"
        },
        "value": {
            "type": "bh.input",
            "value": "owner"
        },
        "resultMapping": {},
        "functionName": "sd_mhRJkOi4nAXRZ0Pe",
        "category": "Storage",
        "x": 345,
        "y": 380,
        "wires": [
            [
                "sd_SgR1KUzFyJAHw2xB"
            ]
        ],
        "__n_excludedFromValidation__": {},
        "generateNext": false,
        "generated": true
    }
]
